README.rst
setup.py
pybars3_extensions/__init__.py
pybars3_extensions.egg-info/PKG-INFO
pybars3_extensions.egg-info/SOURCES.txt
pybars3_extensions.egg-info/dependency_links.txt
pybars3_extensions.egg-info/top_level.txt