Metadata-Version: 1.0
Name: pybars3-extensions
Version: 1.0.0
Summary: pybars3_extensions
Home-page: UNKNOWN
Author: Bogdan Mustiata
Author-email: bogdan.mustiata@gmail.com
License: BSD
Platform: UNKNOWN
